LICENSE
MANIFEST.in
README.md
pyproject.toml
setup.cfg
setup.py
tox.ini
src/Pegasus/DAX3.py
src/Pegasus/__init__.py
src/pegasus_wms.dax.egg-info/PKG-INFO
src/pegasus_wms.dax.egg-info/SOURCES.txt
src/pegasus_wms.dax.egg-info/dependency_links.txt
src/pegasus_wms.dax.egg-info/not-zip-safe
src/pegasus_wms.dax.egg-info/requires.txt
src/pegasus_wms.dax.egg-info/top_level.txt